clogg
